protopunica/BayesClassifier.c
protopunica/BayesClassifier.cp313-win_amd64.pyd
protopunica/BayesClassifier.pyx
protopunica/BayesianNetwork.c
protopunica/BayesianNetwork.cp313-win_amd64.pyd
protopunica/BayesianNetwork.pyx
protopunica/FactorGraph.c
protopunica/FactorGraph.cp313-win_amd64.pyd
protopunica/FactorGraph.pyx
protopunica/MarkovChain.c
protopunica/MarkovChain.cp313-win_amd64.pyd
protopunica/MarkovChain.pyx
protopunica/MarkovNetwork.c
protopunica/MarkovNetwork.cp313-win_amd64.pyd
protopunica/MarkovNetwork.pyx
protopunica/NaiveBayes.c
protopunica/NaiveBayes.cp313-win_amd64.pyd
protopunica/NaiveBayes.pyx
protopunica/__init__.py
protopunica/base.c
protopunica/base.cp313-win_amd64.pyd
protopunica/base.pxd
protopunica/base.pyx
protopunica/bayes.c
protopunica/bayes.cp313-win_amd64.pyd
protopunica/bayes.pxd
protopunica/bayes.pyx
protopunica/callbacks.py
protopunica/gmm.c
protopunica/gmm.cp313-win_amd64.pyd
protopunica/gmm.pyx
protopunica/hmm.c
protopunica/hmm.cp313-win_amd64.pyd
protopunica/hmm.pyx
protopunica/io.py
protopunica/kmeans.c
protopunica/kmeans.cp313-win_amd64.pyd
protopunica/kmeans.pyx
protopunica/parallel.c
protopunica/parallel.cp313-win_amd64.pyd
protopunica/parallel.pyx
protopunica/utils.c
protopunica/utils.cp313-win_amd64.pyd
protopunica/utils.pxd
protopunica/utils.pyx
protopunica/distributions/BernoulliDistribution.c
protopunica/distributions/BernoulliDistribution.cp313-win_amd64.pyd
protopunica/distributions/BernoulliDistribution.pxd
protopunica/distributions/BernoulliDistribution.pyx
protopunica/distributions/BetaDistribution.c
protopunica/distributions/BetaDistribution.cp313-win_amd64.pyd
protopunica/distributions/BetaDistribution.pxd
protopunica/distributions/BetaDistribution.pyx
protopunica/distributions/ConditionalProbabilityTable.c
protopunica/distributions/ConditionalProbabilityTable.cp313-win_amd64.pyd
protopunica/distributions/ConditionalProbabilityTable.pxd
protopunica/distributions/ConditionalProbabilityTable.pyx
protopunica-0.14.8.post2.dist-info/LICENSE
protopunica-0.14.8.post2.dist-info/METADATA
protopunica-0.14.8.post2.dist-info/WHEEL
protopunica-0.14.8.post2.dist-info/top_level.txt
protopunica-0.14.8.post2.dist-info/RECORD
